onediffx/__init__.py
onediffx/_version.py
onediffx/compilers/__init__.py
onediffx/compilers/diffusion_pipeline_compiler.py
onediffx/deep_cache/__init__.py
onediffx/deep_cache/pipeline_stable_diffusion.py
onediffx/deep_cache/pipeline_stable_diffusion_xl.py
onediffx/deep_cache/pipeline_stable_video_diffusion.py
onediffx/deep_cache/models/__init__.py
onediffx/deep_cache/models/fast_unet_2d_condition.py
onediffx/deep_cache/models/fast_unet_spatio_temporal_condition.py
onediffx/deep_cache/models/pipeline_utils.py
onediffx/deep_cache/models/unet_2d_blocks.py
onediffx/deep_cache/models/unet_2d_condition.py
onediffx/deep_cache/models/unet_3d_blocks.py
onediffx/deep_cache/models/unet_spatio_temporal_condition.py
onediffx/lora/__init__.py
onediffx/lora/lora.py
onediffx/lora/state_dict_utils.py
onediffx/lora/text_encoder.py
onediffx/lora/unet.py
onediffx/lora/utils.py
onediffx/utils/__init__.py
onediffx/utils/patch_image_processor.py
onediffx-1.2.0.dist-info/METADATA
onediffx-1.2.0.dist-info/WHEEL
onediffx-1.2.0.dist-info/top_level.txt
onediffx-1.2.0.dist-info/RECORD
