Metadata-Version: 2.1
Name: onediffx
Version: 1.2.0
Summary: onediff extensions for diffusers
Home-page: https://github.com/siliconflow/onediff
Author: OneDiff contributors
Author-email: contact@siliconflow.com
License: Apache-2.0
Classifier: Development Status :: 5 - Production/Stable
Classifier: Intended Audience :: Developers
Classifier: Intended Audience :: Education
Classifier: Intended Audience :: Science/Research
Classifier: License :: OSI Approved :: Apache Software License
Classifier: Operating System :: OS Independent
Classifier: Programming Language :: Python :: 3
Classifier: Programming Language :: Python :: 3.8
Classifier: Programming Language :: Python :: 3.9
Classifier: Programming Language :: Python :: 3.10
Classifier: Topic :: Scientific/Engineering :: Artificial Intelligence
Requires-Python: >=3.7.0
Requires-Dist: transformers >=4.27.1
Requires-Dist: diffusers >=0.19.3
Requires-Dist: accelerate
Requires-Dist: torch
Requires-Dist: onefx
Requires-Dist: omegaconf
